{
  "archive_notes": [
    {
      "url": "pasted://d1ae6f19f5e4babc",
      "title": "1년도 안된 깐부 회동…\"젠슨 황이 또\" 줄줄이 '들썩'",
      "content_type": "news",
      "score": 78,
      "favorite": false,
      "tags": [
        "뉴스",
        "기사",
        "팩트체크"
      ],
      "note": "# 🧠 AI 지식 리포트: 1년도 안된 깐부 회동…\"젠슨 황이 또\" 줄줄이 '들썩'\n\n> 📌 글을 직접 붙여넣으면 링크 조회보다 본문 중심으로 더 잘 정리돼요.  \n> 이 메모는 뉴스 전문을 나중에 다시 읽기 좋게 `핵심 사실 → 수치 → 맥락 → 확인 포인트` 구조로 재구성한 초안입니다.\n\n## 0. 문서 정보\n- 문서 유형: 뉴스/기사\n- 콘텐츠 유형: 뉴스/기사\n- 신뢰도 점수: 78점\n- 광고 위험도: 낮음\n- 작성자 유형: 기록형\n- URL/출처: pasted://d1ae6f19f5e4babc\n- 선택 태그: 없음\n\n## 1. 핵심 요약\n- 1년도 안된 깐부 회동…\"젠슨 황이 또\" 줄줄이 '들썩'\n- 2026.05.29. 오후 8:33\n- 2026.05.29. 오후 10:29\n- 지난해 10월 엔비디아와 삼성전자, 현대차 수장의 치맥 회동.\n- 젠슨 황 엔비디아 CEO가 15년 만에 방한한 데다 국내 대표 기업들과의 협력 구축이란 의미에서 큰 관심을 모았습니다.\n\n## 2. 주요 수치·사실 데이터\n| 항목 | 원문 수치/사실 | 메모 |\n|---|---|---|\n| 주요 데이터 | 1년도 안된 깐부 회동…\"젠슨 황이 또\" 줄줄이 '들썩' | 원문 기준 확인 |\n| 주요 데이터 | 지난해 10월 엔비디아와 삼성전자, 현대차 수장의 치맥 회동. | 원문 기준 확인 |\n| 주요 데이터 | 젠슨 황 엔비디아 CEO가 15년 만에 방한한 데다 국내 대표 기업들과의 협력 구축이란 의미에서 큰 관심을 모았습니다. | 원문 기준 확인 |\n| 주요 데이터 | [젠슨 황/엔비디아 CEO (지난 1월, CES 2026) : 여기 LG가 있습니다. 그들은 방금 새로운 로봇을 발표했습니다. 보스턴다이나믹스(현대차 계열사), 엄청납니다.] | 원문 기준 확인 |\n| 주요 데이터 | 엔비디아와 피지컬 AI 협력 방안을 논의할 것으로 예상되는 LG전자의 주가는 상한가를 기록하며 29만 3천 원까지 올랐고, 네이버와 현대차도 각각 14%, 6% 급등했습니다. | 원문 기준 확인 |\n| 주요 데이터 | 삼성전자는 HBM4를 세계 최초로 양산한 지 두 달 만에 성능이 개선된 HBM4E 샘플을 처음으로 출하했다는 소식에 5.8% 올랐습니다. | 원문 기준 확인 |\n| 주요 데이터 | 중동전쟁 종전 기대감도 반영된 코스피는 어제(28일)보다 3.5% 오른 8,476으로 마감하며 사상 최고치를 또 한 번 경신했습니다. | 원문 기준 확인 |\n| 주요 데이터 | 아스팔트 부풀고 '뻥'…\"딱 봐도 휘었다\" 3년째 아찔 | 원문 기준 확인 |\n| 주요 데이터 | \"떴다방\" \"30년 구형\" \"허위사실\"…장외 비방전 | 원문 기준 확인 |\n| 주요 데이터 | \"떴다방\" \"30년 구형\" \"허위사실\"…장외 비방전동영상 뉴스 | 원문 기준 확인 |\n\n\n## 3. 기사 흐름 정리\n- 로봇과 자율주행 등 피지컬 AI 생태계에 본격적으로 뛰어든 엔비디아는 여러 차례 우리 기업들에 대한 관심을 드러냈습니다.\n- [젠슨 황/엔비디아 CEO (지난 1월, CES 2026) : 여기 LG가 있습니다. 그들은 방금 새로운 로봇을 발표했습니다. 보스턴다이나믹스(현대차 계열사), 엄청납니다.]\n- 이번 방한에선 구광모 LG그룹 회장과 이해진 네이버 의장, 정의선 현대차그룹 회장, 최태원 SK그룹 회장을 만나는 걸로 알려졌습니다.\n- 엔비디아와 피지컬 AI 협력 방안을 논의할 것으로 예상되는 LG전자의 주가는 상한가를 기록하며 29만 3천 원까지 올랐고, 네이버와 현대차도 각각 14%, 6% 급등했습니다.\n- [최건/한국투자증권 수석연구원 : 모터나 이런 제조업 부품 기술력을 가지고 있는, AI 인프라를 충분히 갖춘 나라가 우리나라이기 때문에….]\n- 삼성전자는 HBM4를 세계 최초로 양산한 지 두 달 만에 성능이 개선된 HBM4E 샘플을 처음으로 출하했다는 소식에 5.8% 올랐습니다.\n- 차세대 메모리 시장을 선점했단 평가에 삼성전자는 처음으로 시가총액 2천조 원을 돌파했습니다.\n- 중동전쟁 종전 기대감도 반영된 코스피는 어제(28일)보다 3.5% 오른 8,476으로 마감하며 사상 최고치를 또 한 번 경신했습니다.\n- 거래 대금은 사상 최대인 78조 원을 넘겼고, 시가총액도 7천조 원에 바짝 다가섰습니다.\n\n## 4. 맥락 해석\n- 이 기사는 사전투표 첫날 투표율이 과거 지방선거 대비 높은 수준인지 확인하는 데 의미가 있어요.\n- 단순히 “역대 최고”라는 표현만 볼 것이 아니라, 대선·총선과의 차이, 지역별 편차, 최종 사전투표율 변화 가능성을 함께 봐야 해요.\n- 기사 안에서도 선관위 관계자는 첫날 투표율만으로 유의미한 상승이라고 단정하기는 어렵다고 설명하고 있어요.\n\n## 5. 신뢰성 체크 포인트\n- 중앙선거관리위원회 발표 수치인지 확인\n- 기사 입력/수정 시점 확인\n- 첫날 투표율과 최종 투표율을 구분\n- 지방선거, 대선, 총선의 투표율 비교 기준 구분\n- 지역별 투표율 수치 재확인\n\n## 6. 나중에 활용할 포인트\n- 선거 참여율 변화 분석\n- 지역별 정치 관심도 비교\n- 기사 기반 요약/리포트 작성\n- 통계 수치 인용 자료\n- 공공정보 신뢰도 판단 사례\n\n## 7. 추천 태그\n- 뉴스/기사\n- 선거\n- 사전투표\n- 투표율\n- 공공정보\n",
      "saved_at": "2026-05-29 23:08"
    },
    {
      "url": "https://n.news.naver.com/article/055/0001360285?sid=104",
      "title": "미국, 협상 중대국면서 이란 석유 관련 제재 강화",
      "content_type": "news",
      "score": 78,
      "favorite": false,
      "tags": [
        "뉴스",
        "기사",
        "팩트체크"
      ],
      "note": "# 🧠 AI 지식 리포트: 미국, 협상 중대국면서 이란 석유 관련 제재 강화\n\n> 📌 글을 직접 붙여넣으면 링크 조회보다 본문 중심으로 더 잘 정리돼요.  \n> 이 메모는 뉴스 전문을 나중에 다시 읽기 좋게 `핵심 사실 → 수치 → 맥락 → 확인 포인트` 구조로 재구성한 초안입니다.\n\n## 0. 문서 정보\n- 문서 유형: 뉴스/기사\n- 콘텐츠 유형: 뉴스/기사\n- 신뢰도 점수: 78점\n- 광고 위험도: 낮음\n- 작성자 유형: 기록형\n- URL/출처: https://n.news.naver.com/article/055/0001360285?sid=104\n- 선택 태그: 없음\n\n## 1. 핵심 요약\n- 오후 10시~11시까지 집계한 결과입니다.\n- 이 대통령, 청와대 인근서 사전투표…투표 후엔 깜짝 식사 소통\n- 삼전 시총 2000조 시대 열었다…코스피 8476 또 신기록\n- 분양가 10년 새 2배↑…서울·대구 등 대도시 상승세 주도\n- 6·3 지선 사전투표 첫날 최종 11.6%… 서울은 평균 이하, 대구는 최저치\n\n## 2. 주요 수치·사실 데이터\n| 항목 | 원문 수치/사실 | 메모 |\n|---|---|---|\n| 주요 데이터 | 오후 10시~11시까지 집계한 결과입니다. | 원문 기준 확인 |\n| 주요 데이터 | 분양가 10년 새 2배↑…서울·대구 등 대도시 상승세 주도 | 원문 기준 확인 |\n| 주요 데이터 | 6·3 지선 사전투표 첫날 최종 11.6%… 서울은 평균 이하, 대구는 최저치 | 원문 기준 확인 |\n| 주요 데이터 | 1일차 사전투표율, 지방선거 역대 최고치‥영호남 온도차 '뚜렷' | 원문 기준 확인 |\n| 주요 데이터 | 오후 8시~11시까지 집계한 결과입니다. | 원문 기준 확인 |\n| 주요 데이터 | 사전투표 첫날 투표율 11.6%…지방선거 역대 최고치 | 원문 기준 확인 |\n\n\n## 3. 기사 흐름 정리\n- 인천시 교육감 “3파전…지지층 결집 총력전”\n- '이재명 소년원' 허위 유포 모스탄, 투표소 등장하더니…\n- 1일차 사전투표율, 지방선거 역대 최고치‥영호남 온도차 '뚜렷'\n- 오후 8시~11시까지 집계한 결과입니다.\n- 사전투표 첫날 투표율 11.6%…지방선거 역대 최고치\n\n## 4. 맥락 해석\n- 이 기사는 사전투표 첫날 투표율이 과거 지방선거 대비 높은 수준인지 확인하는 데 의미가 있어요.\n- 단순히 “역대 최고”라는 표현만 볼 것이 아니라, 대선·총선과의 차이, 지역별 편차, 최종 사전투표율 변화 가능성을 함께 봐야 해요.\n- 기사 안에서도 선관위 관계자는 첫날 투표율만으로 유의미한 상승이라고 단정하기는 어렵다고 설명하고 있어요.\n\n## 5. 신뢰성 체크 포인트\n- 중앙선거관리위원회 발표 수치인지 확인\n- 기사 입력/수정 시점 확인\n- 첫날 투표율과 최종 투표율을 구분\n- 지방선거, 대선, 총선의 투표율 비교 기준 구분\n- 지역별 투표율 수치 재확인\n\n## 6. 나중에 활용할 포인트\n- 선거 참여율 변화 분석\n- 지역별 정치 관심도 비교\n- 기사 기반 요약/리포트 작성\n- 통계 수치 인용 자료\n- 공공정보 신뢰도 판단 사례\n\n## 7. 추천 태그\n- 뉴스/기사\n- 선거\n- 사전투표\n- 투표율\n- 공공정보\n",
      "saved_at": "2026-05-29 23:14"
    }
  ],
  "search_history": [
    {
      "time": "2026-05-29 23:30",
      "url": "pasted://20260529233046",
      "cache_key": "pasted://20260529233046::unknown::글 붙여넣기로 조회하기",
      "title": "미국, 이란 석유 수출 제재 강화",
      "content_type": "policy",
      "score": 85,
      "source": "new_analysis",
      "input_mode": "글 붙여넣기로 조회하기"
    },
    {
      "time": "2026-05-29 23:30",
      "url": "pasted://20260529233037",
      "cache_key": "pasted://20260529233037::unknown::글 붙여넣기로 조회하기",
      "title": "미국, 이란 석유 수출 제재 강화",
      "content_type": "policy",
      "score": 85,
      "source": "new_analysis",
      "input_mode": "글 붙여넣기로 조회하기"
    },
    {
      "time": "2026-05-29 23:29",
      "url": "https://n.news.naver.com/article/055/0001360285?sid=104",
      "cache_key": "https://n.news.naver.com/article/055/0001360285?sid=104::unknown::링크로 조회하기",
      "title": "미국, 이란 석유 수출 제재 강화",
      "content_type": "policy",
      "score": 85,
      "source": "cache",
      "input_mode": "링크로 조회하기"
    },
    {
      "time": "2026-05-29 23:13",
      "url": "https://n.news.naver.com/article/055/0001360285?sid=104",
      "cache_key": "https://n.news.naver.com/article/055/0001360285?sid=104::unknown::링크로 조회하기::",
      "title": "미국, 협상 중대국면서 이란 석유 관련 제재 강화",
      "content_type": "news",
      "score": 78,
      "source": "cache",
      "input_mode": "링크로 조회하기"
    },
    {
      "time": "2026-05-29 23:11",
      "url": "https://n.news.naver.com/article/055/0001360139?ntype=RANKING",
      "cache_key": "https://n.news.naver.com/article/055/0001360139?ntype=RANKING::unknown::링크로 조회하기::",
      "title": "농약통 옆에 숨진 50대…창고 안에는 친형 부부 시신",
      "content_type": "news",
      "score": 78,
      "source": "cache",
      "input_mode": "링크로 조회하기"
    },
    {
      "time": "2026-05-29 23:10",
      "url": "https://n.news.naver.com/article/055/0001360139?ntype=RANKING",
      "cache_key": "https://n.news.naver.com/article/055/0001360139?ntype=RANKING::unknown::링크로 조회하기::",
      "title": "농약통 옆에 숨진 50대…창고 안에는 친형 부부 시신",
      "content_type": "news",
      "score": 78,
      "source": "cache",
      "input_mode": "링크로 조회하기"
    },
    {
      "time": "2026-05-29 23:10",
      "url": "https://n.news.naver.com/article/055/0001360139?ntype=RANKING",
      "cache_key": "https://n.news.naver.com/article/055/0001360139?ntype=RANKING::unknown::링크로 조회하기::",
      "title": "농약통 옆에 숨진 50대…창고 안에는 친형 부부 시신",
      "content_type": "news",
      "score": 78,
      "source": "cache",
      "input_mode": "링크로 조회하기"
    },
    {
      "time": "2026-05-29 23:08",
      "url": "pasted://d1ae6f19f5e4babc",
      "cache_key": "pasted://d1ae6f19f5e4babc::unknown::글 붙여넣기로 조회하기::",
      "title": "1년도 안된 깐부 회동…\"젠슨 황이 또\" 줄줄이 '들썩'",
      "content_type": "news",
      "score": 78,
      "source": "cache",
      "input_mode": "글 붙여넣기로 조회하기"
    },
    {
      "time": "2026-05-29 23:06",
      "url": "pasted://150dbf23b1242588",
      "cache_key": "pasted://150dbf23b1242588::unknown::글 붙여넣기로 조회하기::",
      "title": "해당 언론사의 선거 섹션 기사입니다.",
      "content_type": "news",
      "score": 78,
      "source": "cache",
      "input_mode": "글 붙여넣기로 조회하기"
    },
    {
      "time": "2026-05-29 23:06",
      "url": "pasted://150dbf23b1242588",
      "cache_key": "pasted://150dbf23b1242588::unknown::글 붙여넣기로 조회하기::",
      "title": "해당 언론사의 선거 섹션 기사입니다.",
      "content_type": "news",
      "score": 78,
      "source": "cache",
      "input_mode": "글 붙여넣기로 조회하기"
    },
    {
      "time": "2026-05-29 23:06",
      "url": "pasted://8462109fde8728da",
      "cache_key": "pasted://8462109fde8728da::unknown::글 붙여넣기로 조회하기::",
      "title": "이별 통보받은 공무원…여친 신상에 '유흥업소 취업' 썼다",
      "content_type": "news",
      "score": 66,
      "source": "cache",
      "input_mode": "글 붙여넣기로 조회하기"
    },
    {
      "time": "2026-05-29 23:06",
      "url": "pasted://8462109fde8728da",
      "cache_key": "pasted://8462109fde8728da::unknown::글 붙여넣기로 조회하기::",
      "title": "이별 통보받은 공무원…여친 신상에 '유흥업소 취업' 썼다",
      "content_type": "news",
      "score": 66,
      "source": "cache",
      "input_mode": "글 붙여넣기로 조회하기"
    }
  ],
  "saved_analyses": [
    {
      "url": "pasted://d1ae6f19f5e4babc",
      "title": "1년도 안된 깐부 회동…\"젠슨 황이 또\" 줄줄이 '들썩'",
      "content_type": "news",
      "score": 78,
      "ad_risk": "low",
      "author_type": "기록형",
      "summary": [
        "1년도 안된 깐부 회동…\"젠슨 황이 또\" 줄줄이 '들썩'",
        "2026.05.29. 오후 8:33",
        "2026.05.29. 오후 10:29"
      ],
      "evidence": {
        "official_source": "공식 도메인/기관명/출처 표현을 로컬 규칙으로 확인했습니다.",
        "ad_signal": "광고 키워드 없음",
        "experience_signal": "본문 내 구체 정보와 상황 묘사를 확인했습니다.",
        "negative_signal": "비판/주의 신호는 본문 표현 기준으로 별도 확인이 필요합니다."
      },
      "tags": [
        "뉴스",
        "기사",
        "팩트체크",
        "하이"
      ],
      "memo": "",
      "favorite": false,
      "saved_at": "2026-05-29 23:08",
      "result": {
        "content_type": "news",
        "score_breakdown": {
          "official_source": 8,
          "recency": 15,
          "source_diversity": 8,
          "ad_free": 15,
          "info_density": 18,
          "experience_specificity": 8,
          "balanced_review": 8,
          "revisit_mention": 0
        },
        "ad_risk": "low",
        "ad_risk_reason": "명시적 광고/협찬 문구를 로컬 규칙으로 확인했습니다.",
        "author_type": "기록형",
        "author_reason": "본문의 사실, 수치, 일정, 정보 나열 비중이 높아 기록형으로 분류했습니다.",
        "is_official": false,
        "official_org": "",
        "tags_positive": [
          "뉴스",
          "기사",
          "팩트체크"
        ],
        "tags_warning": [],
        "summary": [
          "1년도 안된 깐부 회동…\"젠슨 황이 또\" 줄줄이 '들썩'",
          "2026.05.29. 오후 8:33",
          "2026.05.29. 오후 10:29"
        ],
        "evidence": {
          "official_source": "공식 도메인/기관명/출처 표현을 로컬 규칙으로 확인했습니다.",
          "ad_signal": "광고 키워드 없음",
          "experience_signal": "본문 내 구체 정보와 상황 묘사를 확인했습니다.",
          "negative_signal": "비판/주의 신호는 본문 표현 기준으로 별도 확인이 필요합니다."
        },
        "archive_title": "1년도 안된 깐부 회동…\"젠슨 황이 또\" 줄줄이 '들썩'",
        "trust_score": 78
      },
      "updated_at": "2026-05-29 23:19"
    }
  ],
  "feedback_history": [],
  "analysis_cache": {
    "pasted://8462109fde8728da::unknown::글 붙여넣기로 조회하기::": {
      "content_type": "news",
      "score_breakdown": {
        "official_source": 8,
        "recency": 15,
        "source_diversity": 4,
        "ad_free": 15,
        "info_density": 12,
        "experience_specificity": 8,
        "balanced_review": 8,
        "revisit_mention": 0
      },
      "ad_risk": "low",
      "ad_risk_reason": "명시적 광고/협찬 문구를 로컬 규칙으로 확인했습니다.",
      "author_type": "기록형",
      "author_reason": "본문의 사실, 수치, 일정, 정보 나열 비중이 높아 기록형으로 분류했습니다.",
      "is_official": false,
      "official_org": "",
      "tags_positive": [
        "뉴스",
        "기사",
        "팩트체크"
      ],
      "tags_warning": [],
      "summary": [
        "이별 통보받은 공무원…여친 신상에 '유흥업소 취업' 썼다",
        "2026.05.29. 오후 5:03",
        "2026.05.29. 오후 5:21"
      ],
      "evidence": {
        "official_source": "공식 도메인/기관명/출처 표현을 로컬 규칙으로 확인했습니다.",
        "ad_signal": "광고 키워드 없음",
        "experience_signal": "본문 내 구체 정보와 상황 묘사를 확인했습니다.",
        "negative_signal": "비판/주의 신호는 본문 표현 기준으로 별도 확인이 필요합니다."
      },
      "archive_title": "이별 통보받은 공무원…여친 신상에 '유흥업소 취업' 썼다",
      "trust_score": 66
    },
    "pasted://150dbf23b1242588::unknown::글 붙여넣기로 조회하기::": {
      "content_type": "news",
      "score_breakdown": {
        "official_source": 8,
        "recency": 15,
        "source_diversity": 8,
        "ad_free": 15,
        "info_density": 18,
        "experience_specificity": 8,
        "balanced_review": 8,
        "revisit_mention": 0
      },
      "ad_risk": "low",
      "ad_risk_reason": "명시적 광고/협찬 문구를 로컬 규칙으로 확인했습니다.",
      "author_type": "기록형",
      "author_reason": "본문의 사실, 수치, 일정, 정보 나열 비중이 높아 기록형으로 분류했습니다.",
      "is_official": false,
      "official_org": "",
      "tags_positive": [
        "뉴스",
        "기사",
        "팩트체크"
      ],
      "tags_warning": [],
      "summary": [
        "해당 언론사의 선거 섹션 기사입니다.",
        "이 대통령, 투표용지 들고나와 \"반만 찍혀도 괜찮나\"",
        "2026.05.29. 오후 8:09"
      ],
      "evidence": {
        "official_source": "공식 도메인/기관명/출처 표현을 로컬 규칙으로 확인했습니다.",
        "ad_signal": "광고 키워드 없음",
        "experience_signal": "본문 내 구체 정보와 상황 묘사를 확인했습니다.",
        "negative_signal": "비판/주의 신호는 본문 표현 기준으로 별도 확인이 필요합니다."
      },
      "archive_title": "해당 언론사의 선거 섹션 기사입니다.",
      "trust_score": 78
    },
    "pasted://d1ae6f19f5e4babc::unknown::글 붙여넣기로 조회하기::": {
      "content_type": "news",
      "score_breakdown": {
        "official_source": 8,
        "recency": 15,
        "source_diversity": 8,
        "ad_free": 15,
        "info_density": 18,
        "experience_specificity": 8,
        "balanced_review": 8,
        "revisit_mention": 0
      },
      "ad_risk": "low",
      "ad_risk_reason": "명시적 광고/협찬 문구를 로컬 규칙으로 확인했습니다.",
      "author_type": "기록형",
      "author_reason": "본문의 사실, 수치, 일정, 정보 나열 비중이 높아 기록형으로 분류했습니다.",
      "is_official": false,
      "official_org": "",
      "tags_positive": [
        "뉴스",
        "기사",
        "팩트체크"
      ],
      "tags_warning": [],
      "summary": [
        "1년도 안된 깐부 회동…\"젠슨 황이 또\" 줄줄이 '들썩'",
        "2026.05.29. 오후 8:33",
        "2026.05.29. 오후 10:29"
      ],
      "evidence": {
        "official_source": "공식 도메인/기관명/출처 표현을 로컬 규칙으로 확인했습니다.",
        "ad_signal": "광고 키워드 없음",
        "experience_signal": "본문 내 구체 정보와 상황 묘사를 확인했습니다.",
        "negative_signal": "비판/주의 신호는 본문 표현 기준으로 별도 확인이 필요합니다."
      },
      "archive_title": "1년도 안된 깐부 회동…\"젠슨 황이 또\" 줄줄이 '들썩'",
      "trust_score": 78
    },
    "https://n.news.naver.com/article/055/0001360139?ntype=RANKING::unknown::링크로 조회하기::": {
      "content_type": "news",
      "score_breakdown": {
        "official_source": 8,
        "recency": 15,
        "source_diversity": 8,
        "ad_free": 15,
        "info_density": 18,
        "experience_specificity": 8,
        "balanced_review": 8,
        "revisit_mention": 0
      },
      "ad_risk": "low",
      "ad_risk_reason": "명시적 광고/협찬 문구를 로컬 규칙으로 확인했습니다.",
      "author_type": "기록형",
      "author_reason": "본문의 사실, 수치, 일정, 정보 나열 비중이 높아 기록형으로 분류했습니다.",
      "is_official": false,
      "official_org": "",
      "tags_positive": [
        "뉴스",
        "기사",
        "팩트체크"
      ],
      "tags_warning": [],
      "summary": [
        "농약통 옆에 숨진 50대…창고 안에는 친형 부부 시신",
        "메인 뉴스판에서 SBS 주요뉴스를 볼 수 있습니다.",
        "언론사 구독 해지되었습니다."
      ],
      "evidence": {
        "official_source": "공식 도메인/기관명/출처 표현을 로컬 규칙으로 확인했습니다.",
        "ad_signal": "광고 키워드 없음",
        "experience_signal": "본문 내 구체 정보와 상황 묘사를 확인했습니다.",
        "negative_signal": "비판/주의 신호는 본문 표현 기준으로 별도 확인이 필요합니다."
      },
      "archive_title": "농약통 옆에 숨진 50대…창고 안에는 친형 부부 시신",
      "trust_score": 78
    },
    "https://n.news.naver.com/article/055/0001360285?sid=104::unknown::링크로 조회하기::": {
      "content_type": "news",
      "score_breakdown": {
        "official_source": 8,
        "recency": 15,
        "source_diversity": 8,
        "ad_free": 15,
        "info_density": 18,
        "experience_specificity": 8,
        "balanced_review": 8,
        "revisit_mention": 0
      },
      "ad_risk": "low",
      "ad_risk_reason": "명시적 광고/협찬 문구를 로컬 규칙으로 확인했습니다.",
      "author_type": "기록형",
      "author_reason": "본문의 사실, 수치, 일정, 정보 나열 비중이 높아 기록형으로 분류했습니다.",
      "is_official": false,
      "official_org": "",
      "tags_positive": [
        "뉴스",
        "기사",
        "팩트체크"
      ],
      "tags_warning": [],
      "summary": [
        "미국, 협상 중대국면서 이란 석유 관련 제재 강화",
        "메인 뉴스판에서 SBS 주요뉴스를 볼 수 있습니다.",
        "언론사 구독 해지되었습니다."
      ],
      "evidence": {
        "official_source": "공식 도메인/기관명/출처 표현을 로컬 규칙으로 확인했습니다.",
        "ad_signal": "광고 키워드 없음",
        "experience_signal": "본문 내 구체 정보와 상황 묘사를 확인했습니다.",
        "negative_signal": "비판/주의 신호는 본문 표현 기준으로 별도 확인이 필요합니다."
      },
      "archive_title": "미국, 협상 중대국면서 이란 석유 관련 제재 강화",
      "trust_score": 78
    },
    "https://n.news.naver.com/article/055/0001360285?sid=104::unknown::링크로 조회하기": {
      "content_type": "policy",
      "score_breakdown": {
        "official_source": 15,
        "recency": 15,
        "source_diversity": 10,
        "ad_free": 15,
        "info_density": 15,
        "experience_specificity": 0,
        "balanced_review": 0,
        "revisit_mention": 0
      },
      "ad_risk": "low",
      "ad_risk_reason": "본문에 광고 문구나 홍보성이 없어 광고 위험도가 낮다.",
      "author_type": "기록형",
      "author_reason": "본문이 사실을 기록하고 있어 기록형으로 판단된다.",
      "is_official": true,
      "official_org": "SBS",
      "tags_positive": [
        "미국",
        "이란",
        "석유",
        "제재"
      ],
      "tags_warning": [
        "정치",
        "경제"
      ],
      "summary": [
        "미국은 이란의 석유 수출에 대한 제재를 강화했다.",
        "미국 재무부는 이란산 원유와 석유제품을 수송하는 선박 8척을 제재 대상에 추가했다.",
        "이란의 석유 수출은 이란 경제의 생명줄이다."
      ],
      "evidence": {
        "official_source": "SBS",
        "ad_signal": "없음",
        "experience_signal": "없음",
        "negative_signal": "없음"
      },
      "archive_title": "미국, 이란 석유 수출 제재 강화",
      "trust_score": 85
    }
  },
  "draft_cache": {},
  "auto_feedback_stats": {
    "https://m.blog.naver.com/su0215m/224295507764": {
      "ratings": [
        4
      ],
      "trust_votes": [
        "신뢰함"
      ]
    }
  },
  "custom_trust_criteria": [],
  "active_custom_criteria_titles": []
}